.gitignore
.mailmap
.pre-commit-config.yaml
.zenodo.json
LICENCE
README.rst
pyproject.toml
setup.py
.github/workflows/comment-bot.yml
.github/workflows/test.yml
niftypet/CMakeLists.txt
niftypet/Config.cmake.in
niftypet/__init__.py
niftypet/nimpa/CMakeLists.txt
niftypet/nimpa/__init__.py
niftypet/nimpa/_dist_ver.py
niftypet/nimpa/acr/__init__.py
niftypet/nimpa/acr/analysis.py
niftypet/nimpa/acr/ioaux.py
niftypet/nimpa/acr/params.py
niftypet/nimpa/acr/proc.py
niftypet/nimpa/acr/templates.py
niftypet/nimpa/acr_design/core_mumap/acr-bone-screw.png
niftypet/nimpa/acr_design/core_mumap/acr-bottom.png
niftypet/nimpa/acr_design/core_mumap/acr-inserts-bottoms.png
niftypet/nimpa/acr_design/core_mumap/acr-inserts.png
niftypet/nimpa/acr_design/core_mumap/acr-lid0.png
niftypet/nimpa/acr_design/core_mumap/acr-lid1.png
niftypet/nimpa/acr_design/core_mumap/acr-main-cap-0.png
niftypet/nimpa/acr_design/core_mumap/acr-main-cap-1.png
niftypet/nimpa/acr_design/core_mumap/acr-main-cap-2.png
niftypet/nimpa/acr_design/core_mumap/acr-main-compartment.png
niftypet/nimpa/acr_design/core_mumap/acr-screws.png
niftypet/nimpa/acr_design/core_nac/acr-cap.png
niftypet/nimpa/acr_design/core_nac/acr-inserts.png
niftypet/nimpa/acr_design/core_nac/acr-main.png
niftypet/nimpa/acr_design/core_nac/acr-rng.png
niftypet/nimpa/acr_design/rods/acr-rods-ends-water.png
niftypet/nimpa/acr_design/rods/acr-rods-ends.png
niftypet/nimpa/acr_design/rods/acr-rods-water.png
niftypet/nimpa/acr_design/rods/acr-rods.png
niftypet/nimpa/acr_design/sampling/acr-air-sampling.png
niftypet/nimpa/acr_design/sampling/acr-bckg-sampling.png
niftypet/nimpa/acr_design/sampling/acr-bone-sampling.png
niftypet/nimpa/acr_design/sampling/acr-h2o-sampling.png
niftypet/nimpa/acr_design/sampling/acr-hot1-sampling.png
niftypet/nimpa/acr_design/sampling/acr-hot2-sampling.png
niftypet/nimpa/acr_design/sampling/acr-hot3-sampling.png
niftypet/nimpa/acr_design/sampling/acr-hot4-sampling.png
nimpa.egg-info/PKG-INFO
nimpa.egg-info/SOURCES.txt
nimpa.egg-info/dependency_links.txt
nimpa.egg-info/requires.txt
nimpa.egg-info/top_level.txt
