Metadata-Version: 2.1
Name: nimpa
Version: 2.6.1
Summary: CUDA-accelerated Python utilities for high-throughput neuroimage processing and analysis
Author-email: Pawel Markiewicz <p.markiewicz@ucl.ac.uk>
Maintainer-email: Casper da Costa-Luis <casper.dcl@physics.org>
License: Apache-2.0
Project-URL: documentation, https://niftypet.readthedocs.io
Project-URL: repository, https://github.com/NiftyPET/NIMPA
Project-URL: changelog, https://github.com/NiftyPET/NIMPA/releases
Keywords: PET,MR,processing,analysis
Classifier: Development Status :: 5 - Production/Stable
Classifier: Environment :: GPU
Classifier: Environment :: GPU :: NVIDIA CUDA
Classifier: Intended Audience :: Education
Classifier: Intended Audience :: Healthcare Industry
Classifier: Intended Audience :: Science/Research
Classifier: License :: OSI Approved :: Apache Software License
Classifier: Operating System :: Microsoft :: Windows
Classifier: Operating System :: POSIX :: Linux
Classifier: Programming Language :: C
Classifier: Programming Language :: C++
Classifier: Programming Language :: Python :: 3
Classifier: Programming Language :: Python :: 3.7
Classifier: Programming Language :: Python :: 3.8
Classifier: Programming Language :: Python :: 3.9
Classifier: Programming Language :: Python :: 3.10
Classifier: Programming Language :: Python :: 3.11
Classifier: Programming Language :: Python :: 3 :: Only
Classifier: Topic :: Scientific/Engineering :: Medical Science Apps.
Requires-Python: >=3.7
Provides-Extra: dev
Provides-Extra: plot
Provides-Extra: cuda
Provides-Extra: dcm2niix
Provides-Extra: niftyreg
License-File: LICENCE
